script2bundle.py
script2bundle-0.3.0.dist-info/entry_points.txt
script2bundle-0.3.0.dist-info/WHEEL
script2bundle-0.3.0.dist-info/METADATA
script2bundle-0.3.0.dist-info/RECORD
