Metadata-Version: 2.3
Name: script2bundle
Version: 0.3.0
Summary: Generate an application bundle (MacOS) from an executable
Requires-Dist: icnsutil
Project-URL: homepage, https://github.com/andythomas/script2bundle
